assembly_ai/__init__.py
assembly_ai/endpoints.py
assembly_ai/example.py
assembly_ai/walkthroughs.py
assembly_ai_demo-0.0.7.dist-info/LICENSE
assembly_ai_demo-0.0.7.dist-info/METADATA
assembly_ai_demo-0.0.7.dist-info/WHEEL
assembly_ai_demo-0.0.7.dist-info/top_level.txt
assembly_ai_demo-0.0.7.dist-info/RECORD
