Metadata-Version: 2.1
Name: assembly-ai-demo
Version: 0.0.7
Summary: AssemblyAI Python SDK.
Author-email: Afiz <itsafiz@gmail.com>
License: Copyright (c) 2022 Afiz Shaik        
Project-URL: Homepage, https://github.com/afizs/assembly_ai
Project-URL: Bug Tracker, https://github.com/afizs/assembly_ai/issues
Classifier: Programming Language :: Python :: 3
Classifier: License :: OSI Approved :: MIT License
Classifier: Operating System :: OS Independent
Requires-Python: >=3.7
License-File: LICENSE
Requires-Dist: validators
Requires-Dist: typing-extensions
Requires-Dist: requests
